CHANGELOG.rst
CONTRIBUTING.rst
MANIFEST.in
README.rst
setup.cfg
setup.py
cedar_adfs_forked.egg-info/PKG-INFO
cedar_adfs_forked.egg-info/SOURCES.txt
cedar_adfs_forked.egg-info/dependency_links.txt
cedar_adfs_forked.egg-info/not-zip-safe
cedar_adfs_forked.egg-info/requires.txt
cedar_adfs_forked.egg-info/top_level.txt
django_auth_adfs/__init__.py
django_auth_adfs/backend.py
django_auth_adfs/config.py
django_auth_adfs/drf-urls.py
django_auth_adfs/middleware.py
django_auth_adfs/rest_framework.py
django_auth_adfs/signals.py
django_auth_adfs/urls.py
django_auth_adfs/views.py
django_auth_adfs/templates/django_auth_adfs/login_failed.html
docs/Makefile
docs/adfs_3.0_config_guide.rst
docs/adfs_4.0_config_guide.rst
docs/azure_ad_config_guide.rst
docs/changelog.rst
docs/conf.py
docs/config_guides.rst
docs/contributing.rst
docs/demo.rst
docs/faq.rst
docs/index.rst
docs/install.rst
docs/make.bat
docs/middleware.rst
docs/oauth2_explained.rst
docs/rest_framework.rst
docs/settings_ref.rst
docs/troubleshooting.rst
docs/_static/2012/01_add_relying_party.png
docs/_static/2012/02_add_relying_party_wizard_page1.png
docs/_static/2012/03_add_relying_party_wizard_page2.png
docs/_static/2012/04_add_relying_party_wizard_page3.png
docs/_static/2012/05_add_relying_party_wizard_page4.png
docs/_static/2012/06_add_relying_party_wizard_page5.png
docs/_static/2012/07_add_relying_party_wizard_page6.png
docs/_static/2012/08_relying_party_id.png
docs/_static/2012/09_add_relying_party_wizard_page8.png
docs/_static/2012/10_add_relying_party_wizard_page9.png
docs/_static/2012/11_add_relying_party_wizard_review.png
docs/_static/2012/12_add_relying_party_wizard_page11.png
docs/_static/2012/13_configure_claims_page1.png
docs/_static/2012/14_configure_claims_page2.png
docs/_static/2012/15_configure_claims_page3.png
docs/_static/2012/16_configure_claims_page4.png
docs/_static/2016/01_add_app_group.png
docs/_static/2016/02_add_app_group_wizard_page1.png
docs/_static/2016/03_add_native_app.png
docs/_static/2016/04_native_app_access_policy.png
docs/_static/2016/05_review_settings.png
docs/_static/2016/06_wizard_end.png
docs/_static/2016/07_app_group_settings.png
docs/_static/2016/08_add_claim_rules.png
docs/_static/2016/08_add_ldap_attributes_part1.png
